rsa_python/__init__.py
rsa_python/rsa.py
rsa_python-0.1.1.dist-info/LICENSE
rsa_python-0.1.1.dist-info/METADATA
rsa_python-0.1.1.dist-info/WHEEL
rsa_python-0.1.1.dist-info/top_level.txt
rsa_python-0.1.1.dist-info/RECORD
