Metadata-Version: 2.1
Name: rsa-python
Version: 0.1.1
Summary: RSA Encryption
Home-page: https://github.com/TobyCK/rsa_encryption
Author: Toby Connor-Kebbell
License: UNKNOWN
Project-URL: Bug Tracker, https://github.com/TobyCK/rsa_encryption/issues
Platform: UNKNOWN
Classifier: Programming Language :: Python :: 3
Classifier: License :: OSI Approved :: MIT License
Classifier: Operating System :: OS Independent
Requires-Python: >=3.6
License-File: LICENSE
